MANIFEST.in
README.md
pyproject.toml
setup.cfg
setup.py
dash_google_charts/__init__.py
dash_google_charts/_version.py
dash_google_charts.egg-info/PKG-INFO
dash_google_charts.egg-info/SOURCES.txt
dash_google_charts.egg-info/dependency_links.txt
dash_google_charts.egg-info/requires.txt
dash_google_charts.egg-info/top_level.txt
dash_google_charts/_components/AreaChart.py
dash_google_charts/_components/BarChart.py
dash_google_charts/_components/BubbleChart.py
dash_google_charts/_components/Calendar.py
dash_google_charts/_components/CandlestickChart.py
dash_google_charts/_components/ColumnChart.py
dash_google_charts/_components/ComboChart.py
dash_google_charts/_components/GanttChart.py
dash_google_charts/_components/Gauge.py
dash_google_charts/_components/GeoChart.py
dash_google_charts/_components/Histogram.py
dash_google_charts/_components/LineChart.py
dash_google_charts/_components/OrgChart.py
dash_google_charts/_components/PieChart.py
dash_google_charts/_components/Sankey.py
dash_google_charts/_components/ScatterChart.py
dash_google_charts/_components/SteppedAreaChart.py
dash_google_charts/_components/Table.py
dash_google_charts/_components/Timeline.py
dash_google_charts/_components/TreeMap.py
dash_google_charts/_components/WordTree.py
dash_google_charts/_components/__init__.py
dash_google_charts/_components/dash_google_charts.min.js
dash_google_charts/_components/metadata.json