Metadata-Version: 2.1
Name: dash-google-charts
Version: 0.0.3rc1
Summary: Google Charts for Plotly Dash
Home-page: https://github.com/tcbegley/dash-google-charts
Author: Tom Begley
Author-email: tomcbegley@gmail.com
License: Apache Software License
Project-URL: Bug Reports, https://github.com/tcbegley/dash-google-charts/issues
Platform: UNKNOWN
Classifier: Development Status :: 3 - Alpha
Classifier: License :: OSI Approved :: Apache Software License
Classifier: Programming Language :: Python :: 2.7
Classifier: Programming Language :: Python :: 3.5
Classifier: Programming Language :: Python :: 3.6
Classifier: Programming Language :: Python :: 3.7
